[
  {
    "timestamp": "2026-02-22T21:58:08.858629+00:00",
    "channel": "hasanabi",
    "username": "chubby_shark_5",
    "message": "Yeah",
    "display_name": "chubby_shark_5",
    "user_id": "1369548191",
    "subscriber": false,
    "turbo": false,
    "emotes": "",
    "badges": "",
    "color": "#2E8B57",
    "message_id": "e86762a0-8287-4d47-88c7-31515d30809d"
  },
  {
    "timestamp": "2026-02-22T21:58:08.858629+00:00",
    "channel": "hasanabi",
    "username": "peekabew",
    "message": "you have to do /j duhhh",
    "display_name": "peekabew",
    "user_id": "441344352",
    "subscriber": true,
    "turbo": false,
    "emotes": "",
    "badges": "subscriber/24,premium/1",
    "color": "#FF7F50",
    "message_id": "fe1c46d2-6785-4964-b402-37c671d9d95c"
  },
  {
    "timestamp": "2026-02-22T21:58:08.980236+00:00",
    "channel": "hasanabi",
    "username": "enforcerkogami",
    "message": "END JOKE",
    "display_name": "enforcerkogami",
    "user_id": "105651638",
    "subscriber": true,
    "turbo": false,
    "emotes": "",
    "badges": "subscriber/24,destiny-2-final-shape-raid-race/1",
    "color": "#FF0013",
    "message_id": "1775e0b7-d027-42f3-afed-08d265e54113"
  },
  {
    "timestamp": "2026-02-22T21:58:09.105309+00:00",
    "channel": "hasanabi",
    "username": "lolooongg",
    "message": "have you what\u2019s happening in France with Quentin, the dead Nazi ?",
    "display_name": "lolooongg",
    "user_id": "117258407",
    "subscriber": false,
    "turbo": false,
    "emotes": "",
    "badges": "",
    "color": "",
    "message_id": "f7ac4ffe-07fa-4bd9-8e24-59cc73011630"
  },
  {
    "timestamp": "2026-02-22T21:58:09.106315+00:00",
    "channel": "hasanabi",
    "username": "lofijimmy",
    "message": "yes, yes you do",
    "display_name": "lofijimmy",
    "user_id": "159879727",
    "subscriber": false,
    "turbo": false,
    "emotes": "",
    "badges": "premium/1",
    "color": "#8108F3",
    "message_id": "e0f69cc0-9401-401f-ab1d-c74077aae940"
  },
  {
    "timestamp": "2026-02-22T21:58:09.275280+00:00",
    "channel": "hasanabi",
    "username": "madame_lasagna",
    "message": "comedy is legal! @HasanAbi",
    "display_name": "madame_lasagna",
    "user_id": "554946820",
    "subscriber": true,
    "turbo": false,
    "emotes": "",
    "badges": "subscriber/6",
    "color": "#F08080",
    "message_id": "aab48d8c-3a28-400f-a05b-c45cdfbd0ca5"
  },
  {
    "timestamp": "2026-02-22T21:58:09.483318+00:00",
    "channel": "hasanabi",
    "username": "alekzanndrr",
    "message": "LMAO",
    "display_name": "alekzanndrr",
    "user_id": "37962185",
    "subscriber": true,
    "turbo": false,
    "emotes": "",
    "badges": "subscriber/9,jasontheween-7-day-survival/1",
    "color": "#5F9EA0",
    "message_id": "bf67c44b-53d4-4e92-9c75-09fd19275756"
  },
  {
    "timestamp": "2026-02-22T21:58:09.562135+00:00",
    "channel": "hasanabi",
    "username": "moonstonejewel",
    "message": "End joke",
    "display_name": "MoonStoneJewel",
    "user_id": "48419754",
    "subscriber": false,
    "turbo": false,
    "emotes": "",
    "badges": "no_video/1",
    "color": "#FF69B4",
    "message_id": "e83452fb-21fb-4dc5-a787-ed855f71f188"
  },
  {
    "timestamp": "2026-02-22T21:58:09.562135+00:00",
    "channel": "hasanabi",
    "username": "criminalize_usury",
    "message": "Learning",
    "display_name": "criminalize_usury",
    "user_id": "42942869",
    "subscriber": true,
    "turbo": false,
    "emotes": "",
    "badges": "subscriber/60",
    "color": "#8A2BE2",
    "message_id": "61c91517-f55d-44d5-9969-cbc664305b3c"
  },
  {
    "timestamp": "2026-02-22T21:58:09.599738+00:00",
    "channel": "xqc",
    "username": "xqcisthebeststreamerever1",
    "message": "@dusstiii  Copege Copege Copege Copege",
    "display_name": "xqcisthebeststreamerever1",
    "user_id": "1447041421",
    "subscriber": false,
    "turbo": false,
    "emotes": "",
    "badges": "",
    "color": "#FF69B4",
    "message_id": "89a37497-bf13-4124-accd-2991a3b991c9"
  },
  {
    "timestamp": "2026-02-22T21:58:09.787758+00:00",
    "channel": "loltyler1",
    "username": "gr1z_chicago",
    "message": "BigBrother VapeTime",
    "display_name": "gr1z_chicago",
    "user_id": "21923963",
    "subscriber": true,
    "turbo": false,
    "emotes": "1904:0-9",
    "badges": "predictions/pink-2,subscriber/84,premium/1",
    "color": "#0000FF",
    "message_id": "929a65e6-dfa2-4fef-9c6f-89f9cde6c20d"
  },
  {
    "timestamp": "2026-02-22T21:58:09.909404+00:00",
    "channel": "hasanabi",
    "username": "showmeyorkitties",
    "message": "@HasanAbi Yo shits cluttered. no hate doe!",
    "display_name": "ShowMeYorKitties",
    "user_id": "1283369781",
    "subscriber": false,
    "turbo": false,
    "emotes": "",
    "badges": "gp-explorer-3/1",
    "color": "#DAA520",
    "message_id": "aeedcdb6-0280-4ed4-a670-d112a2038e29"
  },
  {
    "timestamp": "2026-02-22T21:58:09.910404+00:00",
    "channel": "hasanabi",
    "username": "kyttajuttu",
    "message": "posting a meme image is a joke? WHAAAT",
    "display_name": "kyttajuttu",
    "user_id": "57038979",
    "subscriber": true,
    "turbo": false,
    "emotes": "",
    "badges": "subscriber/18,raging-wolf-helm/1",
    "color": "#FF0000",
    "message_id": "fb5f1203-18f4-4edb-b41b-fd743899f6c4"
  },
  {
    "timestamp": "2026-02-22T21:58:10.293192+00:00",
    "channel": "hasanabi",
    "username": "shaken_bake",
    "message": "comedy is illegal PepeHands",
    "display_name": "ShakeN_Bake",
    "user_id": "58576330",
    "subscriber": false,
    "turbo": false,
    "emotes": "",
    "badges": "low/1",
    "color": "#2E8B57",
    "message_id": "0587c796-b425-4b11-b115-f443666ab477"
  },
  {
    "timestamp": "2026-02-22T21:58:10.423331+00:00",
    "channel": "xqc",
    "username": "dusstiii",
    "message": "YES THEY WERE THE BETTER TEAM",
    "display_name": "dusstiii",
    "user_id": "634627377",
    "subscriber": false,
    "turbo": false,
    "emotes": "",
    "badges": "",
    "color": "#FF0000",
    "message_id": "603c90c6-6287-4050-aedb-e57a63477860"
  },
  {
    "timestamp": "2026-02-22T21:58:10.423331+00:00",
    "channel": "hasanabi",
    "username": "wispysuraimu",
    "message": "Learning",
    "display_name": "WispySuraimu",
    "user_id": "234295385",
    "subscriber": false,
    "turbo": false,
    "emotes": "",
    "badges": "raging-wolf-helm/1",
    "color": "#2E8B57",
    "message_id": "a79391bc-5c05-4435-8225-106e0d21042d"
  },
  {
    "timestamp": "2026-02-22T21:58:10.547333+00:00",
    "channel": "hasanabi",
    "username": "pincernigensei",
    "message": "END JOKE",
    "display_name": "\u30d4\u30f3\u30b5\u30fc\u4e8c\u5143\u6027_",
    "user_id": "147987610",
    "subscriber": false,
    "turbo": false,
    "emotes": "",
    "badges": "no_video/1",
    "color": "#FF69B4",
    "message_id": "021d72b0-9f5a-47ff-9cb8-6fc76d8728d5"
  },
  {
    "timestamp": "2026-02-22T21:58:10.754473+00:00",
    "channel": "xqc",
    "username": "xxsskid104xx",
    "message": "BAND",
    "display_name": "xxsskid104xx",
    "user_id": "805458757",
    "subscriber": true,
    "turbo": false,
    "emotes": "",
    "badges": "subscriber/12,moments/1",
    "color": "#2E8B57",
    "message_id": "2297392a-7835-465d-b713-fd793ff5741b"
  },
  {
    "timestamp": "2026-02-22T21:58:10.968311+00:00",
    "channel": "hasanabi",
    "username": "eirgor",
    "message": "NOTED it...was...a...joke...",
    "display_name": "Eirgor",
    "user_id": "22366473",
    "subscriber": true,
    "turbo": false,
    "emotes": "",
    "badges": "subscriber/24,path-of-exile-2-badge/1",
    "color": "#8A2BE2",
    "message_id": "9f348615-7e00-468f-acc3-5df517ebe840"
  },
  {
    "timestamp": "2026-02-22T21:58:11.090442+00:00",
    "channel": "hasanabi",
    "username": "omega_pwner_",
    "message": "Yes :)",
    "display_name": "Omega_Pwner_",
    "user_id": "179231703",
    "subscriber": false,
    "turbo": true,
    "emotes": "1:4-5",
    "badges": "turbo/1",
    "color": "#00FF00",
    "message_id": "cc459c68-40d4-416d-bf58-ec12a490838d"
  },
  {
    "timestamp": "2026-02-22T21:58:11.090442+00:00",
    "channel": "n3on",
    "username": "heddyrn",
    "message": "forgot the drink he said",
    "display_name": "heddyrn",
    "user_id": "657320425",
    "subscriber": false,
    "turbo": true,
    "emotes": "",
    "badges": "turbo/1",
    "color": "#FFFFFF",
    "message_id": "cc2d9e6d-8f60-4b93-9883-09d226ab00a8"
  },
  {
    "timestamp": "2026-02-22T21:58:11.329367+00:00",
    "channel": "hasanabi",
    "username": "ramenoodles413",
    "message": "End joke",
    "display_name": "ramenoodles413",
    "user_id": "246696578",
    "subscriber": true,
    "turbo": false,
    "emotes": "",
    "badges": "subscriber/24,premium/1",
    "color": "",
    "message_id": "9832fe81-ea9e-46dd-87db-29e3e24a6203"
  },
  {
    "timestamp": "2026-02-22T21:58:11.494254+00:00",
    "channel": "hasanabi",
    "username": "david_leonard",
    "message": "@LakeMcGroove, Happ /",
    "display_name": "David_Leonard",
    "user_id": "89646203",
    "subscriber": true,
    "turbo": false,
    "emotes": "",
    "badges": "subscriber/60,twitch-recap-2024/1",
    "color": "#046A38",
    "message_id": "15a573ca-29d0-4f3b-9079-257ada6ed2eb"
  },
  {
    "timestamp": "2026-02-22T21:58:11.638380+00:00",
    "channel": "hasanabi",
    "username": "xxswannie",
    "message": "[end joke]",
    "display_name": "xxswannie",
    "user_id": "475093432",
    "subscriber": true,
    "turbo": false,
    "emotes": "",
    "badges": "subscriber/24,twitch-recap-2023/1",
    "color": "#FF0000",
    "message_id": "8aed5ec3-6b99-42a7-8fd5-6698ede025c6"
  },
  {
    "timestamp": "2026-02-22T21:58:11.711933+00:00",
    "channel": "xqc",
    "username": "nahzug0",
    "message": "!roulette all",
    "display_name": "nahzug0",
    "user_id": "115028142",
    "subscriber": true,
    "turbo": false,
    "emotes": "",
    "badges": "subscriber/54,bits/100",
    "color": "#C61EFF",
    "message_id": "bfc009e0-2698-4be8-b2d1-b57787134054"
  },
  {
    "timestamp": "2026-02-22T21:58:11.711933+00:00",
    "channel": "hasanabi",
    "username": "monstr_uwu",
    "message": "WOOW",
    "display_name": "MONSTR_UwU",
    "user_id": "115651260",
    "subscriber": true,
    "turbo": false,
    "emotes": "",
    "badges": "subscriber/36,superultracombo-2023/1",
    "color": "#DAA520",
    "message_id": "0e5dd86f-2744-4ea9-83ef-3f8ce27ae606"
  },
  {
    "timestamp": "2026-02-22T21:58:11.712933+00:00",
    "channel": "hasanabi",
    "username": "hasanonme",
    "message": "hasan pls read @eliza_4da_bears Cyring genuinely. idk who she is but..... nvm Cyring",
    "display_name": "hasanonme",
    "user_id": "495333954",
    "subscriber": true,
    "turbo": false,
    "emotes": "",
    "badges": "subscriber/12,clips-leader/2",
    "color": "#FF13F0",
    "message_id": "3b05c7f8-04ce-4826-a3e2-9b5879380f47"
  },
  {
    "timestamp": "2026-02-22T21:58:11.765815+00:00",
    "channel": "n3on",
    "username": "xblade991",
    "message": "Timbo suga show",
    "display_name": "xblade991",
    "user_id": "62344403",
    "subscriber": false,
    "turbo": false,
    "emotes": "",
    "badges": "",
    "color": "#00FF7F",
    "message_id": "901c34cc-1c1d-4e26-be5c-8ded16307be9"
  },
  {
    "timestamp": "2026-02-22T21:58:11.765815+00:00",
    "channel": "hasanabi",
    "username": "danuxvz",
    "message": "LEFTERS LIBBERS NO JOKES",
    "display_name": "danuxvz",
    "user_id": "249370088",
    "subscriber": false,
    "turbo": false,
    "emotes": "",
    "badges": "premium/1",
    "color": "#FF7F50",
    "message_id": "7109f51f-f0ce-4535-bede-5786b27329cb"
  },
  {
    "timestamp": "2026-02-22T21:58:11.893845+00:00",
    "channel": "n3on",
    "username": "basic_benji",
    "message": "your drink",
    "display_name": "basic_benji",
    "user_id": "1359861419",
    "subscriber": false,
    "turbo": false,
    "emotes": "",
    "badges": "",
    "color": "",
    "message_id": "1437cb8c-620e-4bcc-83b9-3645878a0230"
  },
  {
    "timestamp": "2026-02-22T21:58:11.894845+00:00",
    "channel": "n3on",
    "username": "oz5791",
    "message": "drink it",
    "display_name": "oz5791",
    "user_id": "1239785158",
    "subscriber": false,
    "turbo": false,
    "emotes": "",
    "badges": "",
    "color": "",
    "message_id": "63c001d0-0aa0-4825-aff0-8120a44f0436"
  },
  {
    "timestamp": "2026-02-22T21:58:11.894845+00:00",
    "channel": "hasanabi",
    "username": "sirmoose",
    "message": "NOTED",
    "display_name": "sirmoose",
    "user_id": "18982894",
    "subscriber": false,
    "turbo": false,
    "emotes": "",
    "badges": "bits/100",
    "color": "#7400CC",
    "message_id": "b7e301c3-2144-4875-ba12-e05c27c9b0ba"
  },
  {
    "timestamp": "2026-02-22T21:58:11.950380+00:00",
    "channel": "xqc",
    "username": "dusstiii",
    "message": "100%",
    "display_name": "dusstiii",
    "user_id": "634627377",
    "subscriber": false,
    "turbo": false,
    "emotes": "",
    "badges": "",
    "color": "#FF0000",
    "message_id": "46000049-b5fa-44b0-b85a-98a1bdcafb64"
  },
  {
    "timestamp": "2026-02-22T21:58:11.950380+00:00",
    "channel": "hasanabi",
    "username": "voicelessv",
    "message": "HIT EM with the soundboard",
    "display_name": "voicelessv",
    "user_id": "474497299",
    "subscriber": true,
    "turbo": false,
    "emotes": "",
    "badges": "subscriber/2048,sub-gifter/10",
    "color": "#FF69B4",
    "message_id": "e3fb70d9-6f90-4005-b692-7a5a3f0b4c63"
  },
  {
    "timestamp": "2026-02-22T21:58:11.950380+00:00",
    "channel": "xqc",
    "username": "schnozebot",
    "message": "\u0001ACTION nahzug0 won 59946 points in roulette and now has 119892 points! FeelsGoodMan\u0001",
    "display_name": "SchnozeBot",
    "user_id": "264879410",
    "subscriber": false,
    "turbo": false,
    "emotes": "",
    "badges": "moderator/1",
    "color": "#8A2BE2",
    "message_id": "738ce1fd-1b2c-4e62-bd6c-b59e6c32f794"
  },
  {
    "timestamp": "2026-02-22T21:58:12.011527+00:00",
    "channel": "n3on",
    "username": "otzy2",
    "message": "You held ufc belt with JDM",
    "display_name": "otzy2",
    "user_id": "450720531",
    "subscriber": false,
    "turbo": false,
    "emotes": "",
    "badges": "",
    "color": "#00FF7F",
    "message_id": "c5c4c758-2167-4ad7-91df-19600bba1d65"
  },
  {
    "timestamp": "2026-02-22T21:58:12.140316+00:00",
    "channel": "hasanabi",
    "username": "nicewhitelady",
    "message": "SipTime",
    "display_name": "NiceWhiteLady",
    "user_id": "1424144569",
    "subscriber": true,
    "turbo": false,
    "emotes": "emotesv2_ba5ae4be5c724ca59d649fa713ff0730:0-6",
    "badges": "subscriber/0",
    "color": "#FF69B4",
    "message_id": "596c677f-7e45-4abd-8d21-442ec8beebf8"
  },
  {
    "timestamp": "2026-02-22T21:58:12.259246+00:00",
    "channel": "loltyler1",
    "username": "ninosaur",
    "message": "since T1 has been gone",
    "display_name": "ninosaur",
    "user_id": "62286193",
    "subscriber": true,
    "turbo": false,
    "emotes": "",
    "badges": "subscriber/96",
    "color": "#C24A0A",
    "message_id": "3f0db92a-e5fb-4dfe-85f5-a7039021ada8"
  },
  {
    "timestamp": "2026-02-22T21:58:12.259246+00:00",
    "channel": "hasanabi",
    "username": "saf_0_",
    "message": "END JOKE!",
    "display_name": "saf_0_",
    "user_id": "73045446",
    "subscriber": true,
    "turbo": false,
    "emotes": "",
    "badges": "subscriber/9,share-the-love/1",
    "color": "#FF0000",
    "message_id": "8623bb9a-fc7b-45ca-895e-c353abe6ea93"
  },
  {
    "timestamp": "2026-02-22T21:58:12.260245+00:00",
    "channel": "hasanabi",
    "username": "anniemaybeok",
    "message": "soundboard time",
    "display_name": "anniemaybeok",
    "user_id": "1213143316",
    "subscriber": true,
    "turbo": false,
    "emotes": "",
    "badges": "subscriber/6,premium/1",
    "color": "#FF7F50",
    "message_id": "59cc0a1a-9ff9-47f1-b5ce-99961d594bfa"
  },
  {
    "timestamp": "2026-02-22T21:58:12.627162+00:00",
    "channel": "hasanabi",
    "username": "ayeayyaron",
    "message": "hasRant",
    "display_name": "ayeayyaron",
    "user_id": "911414503",
    "subscriber": true,
    "turbo": false,
    "emotes": "emotesv2_e31d5f187ccc44d38ed8633f1eb9b51c:0-6",
    "badges": "subscriber/30,twitch-recap-2023/1",
    "color": "#008000",
    "message_id": "b3f706e9-c6b9-4c2f-a260-a08471ebb98f"
  },
  {
    "timestamp": "2026-02-22T21:58:12.751409+00:00",
    "channel": "hasanabi",
    "username": "duketastrophe",
    "message": "PepoG",
    "display_name": "duketastrophe",
    "user_id": "31080064",
    "subscriber": false,
    "turbo": false,
    "emotes": "",
    "badges": "",
    "color": "#1F7A43",
    "message_id": "7adf7b11-9882-4918-b230-1c38ade2eb12"
  },
  {
    "timestamp": "2026-02-22T21:58:12.863893+00:00",
    "channel": "hasanabi",
    "username": "denizenofthevoid",
    "message": "they wont get it though",
    "display_name": "DenizenOfTheVoid",
    "user_id": "855360836",
    "subscriber": true,
    "turbo": false,
    "emotes": "",
    "badges": "subscriber/2",
    "color": "#9ACD32",
    "message_id": "6c55b837-7c0d-4c90-98cb-f91169f0ead2"
  },
  {
    "timestamp": "2026-02-22T21:58:12.987287+00:00",
    "channel": "hasanabi",
    "username": "ewwewww",
    "message": "YEP",
    "display_name": "ewwewww",
    "user_id": "481056013",
    "subscriber": false,
    "turbo": false,
    "emotes": "",
    "badges": "",
    "color": "",
    "message_id": "55006e73-e347-41bf-b92d-1012b60f9ba1"
  },
  {
    "timestamp": "2026-02-22T21:58:13.113509+00:00",
    "channel": "hasanabi",
    "username": "justin_case19",
    "message": "NODDERS",
    "display_name": "Justin_Case19",
    "user_id": "269439157",
    "subscriber": true,
    "turbo": false,
    "emotes": "",
    "badges": "subscriber/12,subtember-2025/1",
    "color": "#00FF7F",
    "message_id": "e901cf65-d77c-4a18-bbf6-c0bcdd530820"
  },
  {
    "timestamp": "2026-02-22T21:58:13.113509+00:00",
    "channel": "hasanabi",
    "username": "mikester96",
    "message": "NOTED",
    "display_name": "mikester96",
    "user_id": "571128756",
    "subscriber": true,
    "turbo": false,
    "emotes": "",
    "badges": "subscriber/36,subtember-2025/1",
    "color": "#A422B3",
    "message_id": "821ba0af-29bd-473a-832c-81ebcd583071"
  },
  {
    "timestamp": "2026-02-22T21:58:13.402390+00:00",
    "channel": "hasanabi",
    "username": "heliotropetroupe",
    "message": "Its wine time on the east coast. Iggy",
    "display_name": "heliotropetroupe",
    "user_id": "1366091367",
    "subscriber": true,
    "turbo": false,
    "emotes": "",
    "badges": "subscriber/0",
    "color": "",
    "message_id": "7abb6239-40b2-4197-b35e-7402872e76d0"
  },
  {
    "timestamp": "2026-02-22T21:58:13.519949+00:00",
    "channel": "hasanabi",
    "username": "sectehking",
    "message": "YEP",
    "display_name": "sectehking",
    "user_id": "29646871",
    "subscriber": true,
    "turbo": false,
    "emotes": "",
    "badges": "subscriber/36,destiny-2-final-shape-raid-race/1",
    "color": "#FF0000",
    "message_id": "01aed82f-273a-428d-ba2d-5a67029a0667"
  },
  {
    "timestamp": "2026-02-22T21:58:13.519949+00:00",
    "channel": "hasanabi",
    "username": "zenzscott",
    "message": "We're still getting used to comedy being legal",
    "display_name": "ZenzScott",
    "user_id": "55794533",
    "subscriber": false,
    "turbo": false,
    "emotes": "",
    "badges": "",
    "color": "#D2691E",
    "message_id": "d55aca57-3aea-469d-afd5-864924ae74db"
  },
  {
    "timestamp": "2026-02-22T21:58:13.709540+00:00",
    "channel": "hasanabi",
    "username": "yoka____",
    "message": "NOTED",
    "display_name": "yoka____",
    "user_id": "79004091",
    "subscriber": true,
    "turbo": false,
    "emotes": "",
    "badges": "subscriber/12",
    "color": "#FF69B4",
    "message_id": "2766ca28-60e0-4a4a-a230-0abaadd7f586"
  },
  {
    "timestamp": "2026-02-22T21:58:13.821732+00:00",
    "channel": "hasanabi",
    "username": "cocobinga",
    "message": "Learning",
    "display_name": "\ub9cc\ub450\uc3d9\ub9cc\ub450\uc3d9\ucf54\ucf54",
    "user_id": "72387827",
    "subscriber": true,
    "turbo": false,
    "emotes": "",
    "badges": "subscriber/18,gp-explorer-3/1",
    "color": "#2E8B57",
    "message_id": "37d71130-9a90-4b8d-b698-a125c5f897cb"
  },
  {
    "timestamp": "2026-02-22T21:58:13.946389+00:00",
    "channel": "hasanabi",
    "username": "kazuki_1313",
    "message": "c'mon bro don't act surprised KEKebab",
    "display_name": "kazuki_1313",
    "user_id": "49371865",
    "subscriber": false,
    "turbo": false,
    "emotes": "",
    "badges": "glitchcon2020/1",
    "color": "#008000",
    "message_id": "667a8cb6-4471-4780-8715-57c3c9817105"
  },
  {
    "timestamp": "2026-02-22T21:58:13.946389+00:00",
    "channel": "hasanabi",
    "username": "rehan072",
    "message": "jok when go haha",
    "display_name": "rehan072",
    "user_id": "538179694",
    "subscriber": true,
    "turbo": false,
    "emotes": "",
    "badges": "subscriber/6,gp-explorer-3/1",
    "color": "#FF0000",
    "message_id": "2da26763-8d05-4798-8a4b-01bc318d36e4"
  },
  {
    "timestamp": "2026-02-22T21:58:13.947388+00:00",
    "channel": "hasanabi",
    "username": "ezio1501",
    "message": "ironmouseNodders",
    "display_name": "Ezio1501",
    "user_id": "146909444",
    "subscriber": true,
    "turbo": false,
    "emotes": "emotesv2_a260176dafee471782f140b17e6339ae:0-15",
    "badges": "subscriber/9,overwatch-league-insider_2019A/1",
    "color": "#A52525",
    "message_id": "f3082452-cb95-4d14-bb69-c98048998520"
  },
  {
    "timestamp": "2026-02-22T21:58:14.067369+00:00",
    "channel": "n3on",
    "username": "2jz47",
    "message": "drink lol",
    "display_name": "2jz47",
    "user_id": "1338294769",
    "subscriber": false,
    "turbo": false,
    "emotes": "",
    "badges": "",
    "color": "#FF69B4",
    "message_id": "48be0812-e42d-4eb9-9a39-50216a35e203"
  },
  {
    "timestamp": "2026-02-22T21:58:14.067369+00:00",
    "channel": "hasanabi",
    "username": "eatingpbj",
    "message": "@HasanAbi ALT TEXT PLEASE!!!!!!!!!!!!",
    "display_name": "eatingpbj",
    "user_id": "473825215",
    "subscriber": true,
    "turbo": false,
    "emotes": "",
    "badges": "subscriber/9,premium/1",
    "color": "#FF0000",
    "message_id": "cdaf1a5e-279d-492c-9049-63fb2e020779"
  },
  {
    "timestamp": "2026-02-22T21:58:14.286300+00:00",
    "channel": "hasanabi",
    "username": "bourgeoisiehater",
    "message": "WHAT'S A JOKE?",
    "display_name": "BourgeoisieHater",
    "user_id": "822690447",
    "subscriber": true,
    "turbo": false,
    "emotes": "",
    "badges": "subscriber/18",
    "color": "",
    "message_id": "5b4bb81e-48af-4d34-a1f7-b4ac54739520"
  },
  {
    "timestamp": "2026-02-22T21:58:14.422135+00:00",
    "channel": "n3on",
    "username": "leanheadassbitvh",
    "message": "the drink",
    "display_name": "leanheadassbitvh",
    "user_id": "1365788391",
    "subscriber": false,
    "turbo": false,
    "emotes": "",
    "badges": "",
    "color": "",
    "message_id": "277e4f49-ccb3-409f-a13e-77da39d3b71b"
  },
  {
    "timestamp": "2026-02-22T21:58:14.422135+00:00",
    "channel": "n3on",
    "username": "isaac_3800",
    "message": "your drink",
    "display_name": "isaac_3800",
    "user_id": "628343303",
    "subscriber": false,
    "turbo": false,
    "emotes": "",
    "badges": "twitch-recap-2023/1",
    "color": "#FF0000",
    "message_id": "d65c1f39-2c8f-4d0d-bee9-4d8bd55c8975"
  },
  {
    "timestamp": "2026-02-22T21:58:14.423134+00:00",
    "channel": "n3on",
    "username": "n3on6969696969",
    "message": "LUL LUL",
    "display_name": "N3on6969696969",
    "user_id": "1412146348",
    "subscriber": true,
    "turbo": false,
    "emotes": "425618:0-2,4-6",
    "badges": "subscriber/0",
    "color": "",
    "message_id": "5ea5a23f-c7dd-4ddd-8dba-c6da008f76ef"
  },
  {
    "timestamp": "2026-02-22T21:58:14.553132+00:00",
    "channel": "n3on",
    "username": "ogkushaholicc",
    "message": "your drink",
    "display_name": "ogkushaholicc",
    "user_id": "943760735",
    "subscriber": true,
    "turbo": false,
    "emotes": "",
    "badges": "subscriber/6,premium/1",
    "color": "#00FF7F",
    "message_id": "102bd20c-c9e6-4ab6-930e-10277cdf0499"
  },
  {
    "timestamp": "2026-02-22T21:58:14.773878+00:00",
    "channel": "hasanabi",
    "username": "mangorangoe",
    "message": "don't listen to them, you're very funny. I died laughing with the tallocide bit",
    "display_name": "MangoRangoe",
    "user_id": "44931387",
    "subscriber": true,
    "turbo": false,
    "emotes": "",
    "badges": "subscriber/24",
    "color": "#DAA520",
    "message_id": "ab0057d7-08f0-4b40-b9a8-bf5143d6ae10"
  },
  {
    "timestamp": "2026-02-22T21:58:14.892916+00:00",
    "channel": "hasanabi",
    "username": "lumirecious",
    "message": "where /j ????????",
    "display_name": "Lumirecious",
    "user_id": "50347392",
    "subscriber": true,
    "turbo": false,
    "emotes": "",
    "badges": "subscriber/2,no_video/1",
    "color": "#FFBDF9",
    "message_id": "d0f286f6-b4d2-4863-a642-3c261943b7ad"
  },
  {
    "timestamp": "2026-02-22T21:58:15.010926+00:00",
    "channel": "hasanabi",
    "username": "daithib725",
    "message": "yes",
    "display_name": "daithib725",
    "user_id": "43238602",
    "subscriber": false,
    "turbo": false,
    "emotes": "",
    "badges": "twitch-recap-2023/1",
    "color": "#FF0000",
    "message_id": "817fa6fb-1077-4f95-aa5a-fefa442e87cc"
  },
  {
    "timestamp": "2026-02-22T21:58:15.134309+00:00",
    "channel": "hasanabi",
    "username": "corocoroman",
    "message": "can we please say that this is not a joke and that this is legit",
    "display_name": "corocoroman",
    "user_id": "1407502811",
    "subscriber": true,
    "turbo": false,
    "emotes": "",
    "badges": "subscriber/2",
    "color": "",
    "message_id": "49afaddd-c479-422e-8956-d44c86130103"
  },
  {
    "timestamp": "2026-02-22T21:58:15.134309+00:00",
    "channel": "hasanabi",
    "username": "bigg03",
    "message": "professional misunderstanders should be purged",
    "display_name": "bigg03",
    "user_id": "119309777",
    "subscriber": false,
    "turbo": false,
    "emotes": "",
    "badges": "",
    "color": "#FF69B4",
    "message_id": "b0cd7b9e-f8db-42c5-bfb5-3fcd5dc8ca76"
  },
  {
    "timestamp": "2026-02-22T21:58:15.249254+00:00",
    "channel": "hasanabi",
    "username": "bluebirddaily",
    "message": "TAKES NOTES",
    "display_name": "bluebirddaily",
    "user_id": "426672844",
    "subscriber": true,
    "turbo": false,
    "emotes": "",
    "badges": "subscriber/72,premium/1",
    "color": "#008000",
    "message_id": "0fb938f1-0942-4faf-ac75-d950a216128a"
  },
  {
    "timestamp": "2026-02-22T21:58:15.249254+00:00",
    "channel": "hasanabi",
    "username": "treat_y0_self",
    "message": "omgBruh not the joke explainer segment again",
    "display_name": "treat_y0_self",
    "user_id": "48802413",
    "subscriber": true,
    "turbo": false,
    "emotes": "",
    "badges": "subscriber/66,evo-2025/1",
    "color": "#2E8B57",
    "message_id": "f70d624b-1192-4ece-9bc6-54917b3ed639"
  },
  {
    "timestamp": "2026-02-22T21:58:15.250254+00:00",
    "channel": "hasanabi",
    "username": "colinkilz",
    "message": "make sure you say \"end joke\" @HasanAbi",
    "display_name": "colinkilz",
    "user_id": "170031881",
    "subscriber": true,
    "turbo": false,
    "emotes": "",
    "badges": "subscriber/18,premium/1",
    "color": "#6D712E",
    "message_id": "85a45671-6516-4b41-ad1f-064817112d7a"
  },
  {
    "timestamp": "2026-02-22T21:58:15.259257+00:00",
    "channel": "hasanabi",
    "username": "carefreegamin",
    "message": "KEKL",
    "display_name": "carefreegamin",
    "user_id": "159882069",
    "subscriber": true,
    "turbo": false,
    "emotes": "",
    "badges": "subscriber/2,bingbonglove/1",
    "color": "#1E90FF",
    "message_id": "5fa3dc42-a67e-43ba-a67e-878cae5b7792"
  },
  {
    "timestamp": "2026-02-22T21:58:15.329455+00:00",
    "channel": "xqc",
    "username": "starkayc",
    "message": "why have a savings account when u can just bet on forsen losing for better yields on polymarket hesRight",
    "display_name": "StarKayC",
    "user_id": "128127443",
    "subscriber": true,
    "turbo": false,
    "emotes": "",
    "badges": "subscriber/36,purple-pixel-heart---together-for-good-24/1",
    "color": "#FF0084",
    "message_id": "da2ede16-534e-4de5-9675-997d28d6a0d1"
  },
  {
    "timestamp": "2026-02-22T21:58:15.330457+00:00",
    "channel": "hasanabi",
    "username": "karlosblack",
    "message": "FAHHHHHHHHHHHH",
    "display_name": "KarlosBlack",
    "user_id": "68911002",
    "subscriber": false,
    "turbo": false,
    "emotes": "",
    "badges": "rplace-2023/1",
    "color": "#8A2BE2",
    "message_id": "57d3760d-fc24-4779-8d23-9abf3f404b4d"
  },
  {
    "timestamp": "2026-02-22T21:58:15.527301+00:00",
    "channel": "hasanabi",
    "username": "popular_knapsack",
    "message": "NOTED",
    "display_name": "Popular_Knapsack",
    "user_id": "129578800",
    "subscriber": true,
    "turbo": false,
    "emotes": "",
    "badges": "subscriber/48,bits-charity/1",
    "color": "#15D7F9",
    "message_id": "23ec5ad8-2e71-415a-b2df-f968c0c5d095"
  },
  {
    "timestamp": "2026-02-22T21:58:15.786217+00:00",
    "channel": "hasanabi",
    "username": "vyre16",
    "message": "clintNotes",
    "display_name": "Vyre16",
    "user_id": "30766231",
    "subscriber": true,
    "turbo": false,
    "emotes": "emotesv2_1e5c6a09e8744e36a84ca43ab669104e:0-9",
    "badges": "subscriber/12",
    "color": "#FF0000",
    "message_id": "76812b7f-f47e-40ec-bcbb-ba8178ca95d3"
  },
  {
    "timestamp": "2026-02-22T21:58:15.876649+00:00",
    "channel": "hasanabi",
    "username": "paragon_of_laziness",
    "message": "NOTED",
    "display_name": "Paragon_of_Laziness",
    "user_id": "48401324",
    "subscriber": true,
    "turbo": false,
    "emotes": "",
    "badges": "subscriber/12",
    "color": "#8A2BE2",
    "message_id": "92107c15-c85a-4743-b51b-b805bc449207"
  },
  {
    "timestamp": "2026-02-22T21:58:15.876649+00:00",
    "channel": "hasanabi",
    "username": "supra_soul",
    "message": "The Flag Kinda THrowing me off ,bro Ngl",
    "display_name": "Supra_Soul",
    "user_id": "159375133",
    "subscriber": false,
    "turbo": false,
    "emotes": "",
    "badges": "",
    "color": "#1E90FF",
    "message_id": "05af62d3-37d0-40ae-b917-7ad2d98ca86c"
  },
  {
    "timestamp": "2026-02-22T21:58:15.877648+00:00",
    "channel": "hasanabi",
    "username": "ghos7dog",
    "message": "YEP explain the joke",
    "display_name": "ghos7dog",
    "user_id": "116956183",
    "subscriber": true,
    "turbo": false,
    "emotes": "",
    "badges": "subscriber/12,mel/1",
    "color": "",
    "message_id": "8aa9ab2c-c164-4170-a241-716d456afec2"
  },
  {
    "timestamp": "2026-02-22T21:58:15.914648+00:00",
    "channel": "hasanabi",
    "username": "saltandpepperpiker",
    "message": "alright im heading to the gym, ill reopen ur stream there i rpomie. im dedicated",
    "display_name": "saltandpepperpiker",
    "user_id": "1439910867",
    "subscriber": false,
    "turbo": false,
    "emotes": "",
    "badges": "no_video/1",
    "color": "#FF0000",
    "message_id": "ea4863c2-2289-4cbc-be63-b858acd98953"
  },
  {
    "timestamp": "2026-02-22T21:58:15.987876+00:00",
    "channel": "hasanabi",
    "username": "niic0h",
    "message": "ALSO ITS POLITICAL HUMOR! who fucking asked will fans?",
    "display_name": "Niic0h",
    "user_id": "964653247",
    "subscriber": true,
    "turbo": false,
    "emotes": "",
    "badges": "subscriber/24",
    "color": "#8A2BE2",
    "message_id": "60ba9888-9283-4c49-b7d7-5e865df96bb8"
  },
  {
    "timestamp": "2026-02-22T21:58:16.113610+00:00",
    "channel": "hasanabi",
    "username": "amaaaaaaaaaaaaaaaa",
    "message": "@HasanAbi what is a joke",
    "display_name": "amaaaaaaaaaaaaaaaa",
    "user_id": "44825876",
    "subscriber": true,
    "turbo": false,
    "emotes": "",
    "badges": "subscriber/2000,sub-gifter/5",
    "color": "#00FF7F",
    "message_id": "5a36b973-60be-4eba-bebe-cad50d3c6b98"
  },
  {
    "timestamp": "2026-02-22T21:58:16.240189+00:00",
    "channel": "hasanabi",
    "username": "lulantifa",
    "message": "KirkLaugh",
    "display_name": "Lulantifa",
    "user_id": "449728418",
    "subscriber": false,
    "turbo": false,
    "emotes": "",
    "badges": "",
    "color": "#1E90FF",
    "message_id": "e803ec6c-e82d-41f4-8859-b42b92595f37"
  },
  {
    "timestamp": "2026-02-22T21:58:16.366176+00:00",
    "channel": "hasanabi",
    "username": "joeleesun",
    "message": "Begin and end joke",
    "display_name": "JoeLeeSun",
    "user_id": "76813090",
    "subscriber": true,
    "turbo": false,
    "emotes": "",
    "badges": "subscriber/42,premium/1",
    "color": "#008800",
    "message_id": "b2edd368-7350-43eb-9ca0-f9014c01d440"
  },
  {
    "timestamp": "2026-02-22T21:58:16.489184+00:00",
    "channel": "n3on",
    "username": "bomboclaaaaaattt",
    "message": "your drink",
    "display_name": "bomboclaaaaaattt",
    "user_id": "1043005074",
    "subscriber": false,
    "turbo": false,
    "emotes": "",
    "badges": "",
    "color": "",
    "message_id": "93c12cf9-c639-4561-9fc7-a997e5e1907b"
  },
  {
    "timestamp": "2026-02-22T21:58:16.490184+00:00",
    "channel": "hasanabi",
    "username": "vinosavage",
    "message": "Every time Im here you do......",
    "display_name": "VinoSavage",
    "user_id": "600374472",
    "subscriber": true,
    "turbo": false,
    "emotes": "",
    "badges": "subscriber/36,premium/1",
    "color": "#FF0000",
    "message_id": "d2e9eec5-efc5-4ab0-ad1b-afd5c0fba872"
  },
  {
    "timestamp": "2026-02-22T21:58:16.610309+00:00",
    "channel": "xqc",
    "username": "johncouro",
    "message": "BAND",
    "display_name": "JohnCouro",
    "user_id": "63490520",
    "subscriber": true,
    "turbo": false,
    "emotes": "",
    "badges": "subscriber/36,borderlands-4-badge---vault-symbol/1",
    "color": "#FFFFFF",
    "message_id": "ef0e75d7-e895-4a94-ab19-16bcde1993ea"
  },
  {
    "timestamp": "2026-02-22T21:58:16.736153+00:00",
    "channel": "hasanabi",
    "username": "twitornot",
    "message": "zachapClap zachapClap zachapClap",
    "display_name": "twitornot",
    "user_id": "1346063108",
    "subscriber": true,
    "turbo": false,
    "emotes": "emotesv2_5e924942b948415b96a11259226ce633:0-9,11-20,22-31",
    "badges": "subscriber/6,subtember-2025/1",
    "color": "#FF69B4",
    "message_id": "57b585af-204f-42e9-b28a-819b92427b4e"
  },
  {
    "timestamp": "2026-02-22T21:58:16.736206+00:00",
    "channel": "hasanabi",
    "username": "twitpenguin",
    "message": "NOTED",
    "display_name": "Twitpenguin",
    "user_id": "65178166",
    "subscriber": false,
    "turbo": false,
    "emotes": "",
    "badges": "premium/1",
    "color": "#EDB7D3",
    "message_id": "86470a0d-1133-4f48-a22a-c7c0ce574ac8"
  },
  {
    "timestamp": "2026-02-22T21:58:16.860067+00:00",
    "channel": "hasanabi",
    "username": "skill_cylinder",
    "message": "Learning",
    "display_name": "Skill_Cylinder",
    "user_id": "54920654",
    "subscriber": true,
    "turbo": false,
    "emotes": "",
    "badges": "subscriber/78",
    "color": "#0C90C0",
    "message_id": "6710a970-fc2e-4051-9f89-44e97438077d"
  },
  {
    "timestamp": "2026-02-22T21:58:16.981123+00:00",
    "channel": "hasanabi",
    "username": "bluhm98",
    "message": "LIBBERS HOGGERS Tssk",
    "display_name": "bluhm98",
    "user_id": "513345724",
    "subscriber": true,
    "turbo": false,
    "emotes": "",
    "badges": "subscriber/12,premium/1",
    "color": "",
    "message_id": "14f6165a-e400-4122-b66f-0f599856db83"
  },
  {
    "timestamp": "2026-02-22T21:58:16.981123+00:00",
    "channel": "hasanabi",
    "username": "michaelhastingsfan",
    "message": "DinkDonk END JOKE",
    "display_name": "MichaelHastingsFan",
    "user_id": "838524590",
    "subscriber": true,
    "turbo": false,
    "emotes": "",
    "badges": "subscriber/6,bingbonglove/1",
    "color": "#DAA520",
    "message_id": "1fc0aa5a-cdc9-4969-b6b0-0bbab3a852c5"
  },
  {
    "timestamp": "2026-02-22T21:58:16.982121+00:00",
    "channel": "hasanabi",
    "username": "lemonwizrd",
    "message": "Learning",
    "display_name": "lemonwizrd",
    "user_id": "401780847",
    "subscriber": true,
    "turbo": false,
    "emotes": "",
    "badges": "subscriber/60,umbrella-corporation/1",
    "color": "#9ACD32",
    "message_id": "bee61edc-46d5-4bff-9bcd-12b270144481"
  },
  {
    "timestamp": "2026-02-22T21:58:17.107589+00:00",
    "channel": "loltyler1",
    "username": "pedrex2121",
    "message": "Red",
    "display_name": "pedrex2121",
    "user_id": "54916145",
    "subscriber": false,
    "turbo": false,
    "emotes": "",
    "badges": "chatter-cs-go-2022/1",
    "color": "#0000FF",
    "message_id": "03ac1157-84da-48ca-ab8a-f427880a4d35"
  },
  {
    "timestamp": "2026-02-22T21:58:17.408646+00:00",
    "channel": "hasanabi",
    "username": "jareermoney",
    "message": "Mhm /s or Mhm end joke @HasanAbi",
    "display_name": "jareermoney",
    "user_id": "1225088369",
    "subscriber": false,
    "turbo": false,
    "emotes": "",
    "badges": "gp-explorer-3/1",
    "color": "#2E8B57",
    "message_id": "0f153846-69ef-4560-b7b9-4da138c94e67"
  },
  {
    "timestamp": "2026-02-22T21:58:17.622783+00:00",
    "channel": "n3on",
    "username": "leanheadassbitvh",
    "message": "take the drink",
    "display_name": "leanheadassbitvh",
    "user_id": "1365788391",
    "subscriber": false,
    "turbo": false,
    "emotes": "",
    "badges": "",
    "color": "",
    "message_id": "3ce4a56d-4782-4f45-9cb3-3da34e326f22"
  },
  {
    "timestamp": "2026-02-22T21:58:17.749464+00:00",
    "channel": "hasanabi",
    "username": "shortasiandude101",
    "message": "NOTED",
    "display_name": "shortasiandude101",
    "user_id": "22227156",
    "subscriber": true,
    "turbo": false,
    "emotes": "",
    "badges": "subscriber/60,premium/1",
    "color": "#0ED3FA",
    "message_id": "b103e7e6-5d8d-4a6d-96a3-a1a606364d40"
  },
  {
    "timestamp": "2026-02-22T21:58:17.834534+00:00",
    "channel": "hasanabi",
    "username": "lofijimmy",
    "message": "thats why youve had to so far hahaha",
    "display_name": "lofijimmy",
    "user_id": "159879727",
    "subscriber": false,
    "turbo": false,
    "emotes": "",
    "badges": "premium/1",
    "color": "#8108F3",
    "message_id": "d9bf3aa8-e7b9-4f36-a8a3-49b5dc900745"
  },
  {
    "timestamp": "2026-02-22T21:58:17.834534+00:00",
    "channel": "hasanabi",
    "username": "zainmoti",
    "message": "YesYes please explain Learning",
    "display_name": "zainmoti",
    "user_id": "1104030417",
    "subscriber": false,
    "turbo": false,
    "emotes": "",
    "badges": "twitch-recap-2025/1",
    "color": "#FF69B4",
    "message_id": "9bc78b9d-a643-42b0-a515-c987cee5598a"
  },
  {
    "timestamp": "2026-02-22T21:58:17.835535+00:00",
    "channel": "hasanabi",
    "username": "skydenxx",
    "message": "PepoG",
    "display_name": "skydenxx",
    "user_id": "567148495",
    "subscriber": true,
    "turbo": false,
    "emotes": "",
    "badges": "subscriber/48",
    "color": "#8A2BE2",
    "message_id": "ff0d5ba0-a9d0-48c4-adf7-b8467311c0fb"
  },
  {
    "timestamp": "2026-02-22T21:58:17.865534+00:00",
    "channel": "n3on",
    "username": "hempwarrior420",
    "message": "LUL LUL LUL LUL",
    "display_name": "HempWarrior420",
    "user_id": "77575581",
    "subscriber": true,
    "turbo": false,
    "emotes": "425618:0-2,4-6,8-10,12-14",
    "badges": "subscriber/0,raging-wolf-helm/1",
    "color": "#1E90FF",
    "message_id": "2bb4ad97-8912-4028-9de2-de39026b76c8"
  },
  {
    "timestamp": "2026-02-22T21:58:18.042613+00:00",
    "channel": "hasanabi",
    "username": "moses898",
    "message": "what is a joke, is it a drink like coke",
    "display_name": "moses898",
    "user_id": "1383509071",
    "subscriber": false,
    "turbo": false,
    "emotes": "",
    "badges": "",
    "color": "",
    "message_id": "329c8272-5d1c-4a99-91c3-1cef058597ef"
  }
]